{
  "type": "Feature",
  "stac_version": "1.0.0",
  "stac_extensions": [
    "https://stac-extensions.github.io/projection/v1.1.0/schema.json"
  ],
  "id": "gha_adm2",
  "geometry": {
    "type": "Polygon",
    "coordinates": [
      [
        [
          -2.0551147459999584,
          4.7407226560000595
        ],
        [
          -2.0919799799999623,
          4.74108886700003
        ],
        [
          -3.108581542999957,
          5.090270996000072
        ],
        [
          -3.262084960999971,
          6.6176757810000595
        ],
        [
          -2.939697265999939,
          10.713500977000024
        ],
        [
          -2.9385986329999696,
          10.71868896500007
        ],
        [
          -2.9370117189999405,
          10.723327637000068
        ],
        [
          -2.833984374999943,
          11.004089355000076
        ],
        [
          -2.7584838869999544,
          11.018920898000033
        ],
        [
          -2.7550048829999696,
          11.01928710900006
        ],
        [
          -0.276306151999961,
          11.17468261700003
        ],
        [
          -0.2512817379999319,
          11.169494629000042
        ],
        [
          -0.01690673799993192,
          11.113708496000072
        ],
        [
          -0.008911132999969595,
          11.109497070000032
        ],
        [
          -0.0051269529999444785,
          11.107482910000044
        ],
        [
          0.024291992000030405,
          11.062316895000038
        ],
        [
          0.3963012700000377,
          10.313476562000062
        ],
        [
          0.39770507800005817,
          10.309509277000075
        ],
        [
          1.2003173830000264,
          6.167724609000061
        ],
        [
          1.1995239260000403,
          6.112670898000033
        ],
        [
          0.9735107420000304,
          5.829711914000029
        ],
        [
          0.970886230000076,
          5.82647705100004
        ],
        [
          0.9678955080000264,
          5.82312011700003
        ],
        [
          0.9635009770000238,
          5.818298340000069
        ],
        [
          0.9490966800000251,
          5.803283691000047
        ],
        [
          0.9437255860000278,
          5.798278809000067
        ],
        [
          0.9415283200000317,
          5.796325684000067
        ],
        [
          0.9384765620000621,
          5.794128418000071
        ],
        [
          0.9360961910000469,
          5.792480469000054
        ],
        [
          0.9331054690000542,
          5.790893555000025
        ],
        [
          0.9295043950000377,
          5.789123535000044
        ],
        [
          0.9254760740000734,
          5.787292480000076
        ],
        [
          0.9216918950000377,
          5.7858886720000555
        ],
        [
          -1.9755859379999379,
          4.7583007810000595
        ],
        [
          -1.9807128909999392,
          4.756896973000039
        ],
        [
          -2.0551147459999584,
          4.7407226560000595
        ]
      ]
    ]
  },
  "bbox": [
    -3.262084960999971,
    4.7407226560000595,
    1.2003173830000264,
    11.17468261700003
  ],
  "properties": {
    "admin_level": "2",
    "languages_admin_self": [
      "en"
    ],
    "languages_admin_all": [
      "en"
    ],
    "iso3": "GHA",
    "iso2": "GH",
    "name": "Ghana",
    "itos_url": "https://codgis.itos.uga.edu/arcgis/rest/services/COD_External/GHA_pcode/FeatureServer",
    "itos_update": "2023-05-17",
    "itos_service": "COD_External",
    "itos_level": 2.0,
    "itos_index_0": 0.0,
    "itos_index_1": 1.0,
    "itos_index_2": 2.0,
    "itos_index_3": null,
    "itos_index_4": null,
    "itos_index_5": null,
    "hdx_url": "https://data.humdata.org/dataset/cod-ab-gha",
    "hdx_date": "2021-03-10",
    "hdx_update": "2023-04-04",
    "hdx_source_1": "Ghana Statistical Services (GSS)",
    "hdx_source_2": "OCHA West and Central Africa (ROWCA)",
    "hdx_license": "Creative Commons Attribution for Intergovernmental Organisations",
    "hdx_caveats": "The projected COD-PS source data maintains the 2010 census administrative structure (with 216 ADM2 features) while the COD-AB reflects the evolved structure (with 260 ADM2 features). However, 187 of the 216 COD-PS features exactly match COD-AB features and are given the corresponding ADM2 P-codes. ADM1 has also evolved since the census, but every COD-PS feature can be P-coded to the COD-PS structure.",
    "start_datetime": "2018-10-26T00:00:00Z",
    "end_datetime": "2021-03-08T00:00:00Z",
    "proj:epsg": 4326,
    "datetime": "2021-03-08T00:00:00Z"
  },
  "links": [
    {
      "rel": "root",
      "href": "../../catalog.json",
      "type": "application/json"
    },
    {
      "rel": "collection",
      "href": "../collection.json",
      "type": "application/json"
    },
    {
      "rel": "parent",
      "href": "../collection.json",
      "type": "application/json"
    }
  ],
  "assets": {
    "parquet": {
      "href": "https://cod-data.fieldmaps.io/assets/level-1/gha_adm2.parquet",
      "type": "application/vnd.apache.parquet",
      "roles": [
        "data"
      ]
    },
    "geojson": {
      "href": "https://cod-api.fieldmaps.io/features/1/gha/2?f=geojson",
      "type": "application/geo+json",
      "roles": [
        "data"
      ]
    },
    "gpkg": {
      "href": "https://cod-api.fieldmaps.io/features/1/gha/2?f=gpkg",
      "type": "application/geopackage+sqlite3",
      "roles": [
        "data"
      ]
    },
    "gpkg.zip": {
      "href": "https://cod-api.fieldmaps.io/features/1/gha/2?f=gpkg.zip",
      "type": "application/geopackage+sqlite3",
      "roles": [
        "data"
      ]
    },
    "kml": {
      "href": "https://cod-api.fieldmaps.io/features/1/gha/2?f=kml",
      "type": "application/vnd.google-earth.kml+xml",
      "roles": [
        "data"
      ]
    },
    "fgb": {
      "href": "https://cod-api.fieldmaps.io/features/1/gha/2?f=fgb",
      "type": "application/vnd.flatgeobuf",
      "roles": [
        "data"
      ]
    },
    "shp.zip": {
      "href": "https://cod-api.fieldmaps.io/features/1/gha/2?f=shp.zip",
      "type": "application/x-shapefile",
      "roles": [
        "data"
      ]
    },
    "gdb.zip": {
      "href": "https://cod-api.fieldmaps.io/features/1/gha/2?f=gdb.zip",
      "type": "application/x-filegdb",
      "roles": [
        "data"
      ]
    },
    "tilejson": {
      "href": "https://cod-tiles.fieldmaps.io/assets/level-1/gha_adm2.json",
      "type": "application/json",
      "roles": [
        "data"
      ]
    },
    "pmtiles": {
      "href": "https://cod-data.fieldmaps.io/assets/level-1/gha_adm2.pmtiles",
      "type": "application/vnd.pmtiles",
      "roles": [
        "data"
      ]
    },
    "webp": {
      "href": "https://cod-data.fieldmaps.io/assets/level-1/gha_adm2.webp",
      "type": "image/webp",
      "roles": [
        "thumbnail",
        "overview"
      ]
    }
  },
  "collection": "cod-ab-1"
}